{
  "tasks": [
    {
    "task": "Выбрать значение тока при котором человек почувствует легкое покалывание",
    "subject": "БЖД",
    "category": "Электричество",
    "difficulty": "Лёгкий",
    "author": "Королев П.Т.",
    "id_task": 1
    },

    {
    "task": "Освещенность рабочего места при боковом освещении составляет Евн=40 (лк).",
    "subject": "БЖД",
    "category": "Электричество",
    "difficulty": "Средний",
    "author": "Трофимов С.Г.",
    "id_task": 2
    },

    {
    "task": "Рассчитать необходимую площадь световых проемов при применении бокового освещения",
    "subject": "БЖД",
    "category": "Электричество",
    "difficulty": "Лёгкий",
    "author": "Птушкин Н.П.",
    "id_task": 3
    },

    {
    "task": "Определить необходимое количество ламп накаливания типа Б для светильников типа ШМ",
    "subject": "БЖД",
    "category": "Электричество",
    "difficulty": "Лёгкий",
    "author": "Фомина Р.С.",
    "id_task": 4
    },

    {
    "task": "Определить необходимое количество люминесцентных ламп дневного света марки «ЛБ»",
    "subject": "БЖД",
    "category": "Электричество",
    "difficulty": "Средний",
    "author": "Птушкин Н.П.",
    "id_task": 5
    },

    {
    "task": "Коэффициент использования светового потока светильника типа ЛБ с учетом коэффициентов",
    "subject": "БЖД",
    "category": "Электричество",
    "difficulty": "Лёгкий",
    "author": "Фомина Р.С.",
    "id_task": 6
    }

    
  ]
}